README.md
setup.cfg
setup.py
omegle_translator/__init__.py
shivank_anchal.egg-info/PKG-INFO
shivank_anchal.egg-info/SOURCES.txt
shivank_anchal.egg-info/dependency_links.txt
shivank_anchal.egg-info/requires.txt
shivank_anchal.egg-info/top_level.txt