Metadata-Version: 2.1
Name: shivank-anchal
Version: 0.0.1
Summary: A small example package,to communicate on omegle in any language
Home-page: https://githuself.b.com/frozenmafia/omego_transo.git
Author: Shivank Anchal
Author-email: shivajay295@gmail.com
License: UNKNOWN
Download-URL: https://github.com/frozenmafia/omegle_translator/archive/0.0.1.tar.gz
Platform: UNKNOWN
Classifier: Programming Language :: Python :: 3
Classifier: License :: OSI Approved :: MIT License
Classifier: Operating System :: OS Independent
Requires-Python: >=3.6
